pythonic_archive_kit/__init__.py
pythonic_archive_kit/base.py
pythonic_archive_kit/libraries.py
pythonic_archive_kit/typing.py
pythonic_archive_kit/utils.py
pythonic_archive_kit-2.0.1.dist-info/LICENSE
pythonic_archive_kit-2.0.1.dist-info/WHEEL
pythonic_archive_kit-2.0.1.dist-info/METADATA
pythonic_archive_kit-2.0.1.dist-info/RECORD
