Metadata-Version: 2.1
Name: pythonic_archive_kit
Version: 2.0.1
Summary: The Pythonic Archive Kit
Author: Alyce Osbourne
Classifier: License :: OSI Approved :: GNU General Public License v3 or later (GPLv3+)
Requires-Dist: cryptography ; extra == "all"
Requires-Dist: dill ; extra == "all"
Requires-Dist: cryptography ; extra == "encryption"
Requires-Dist: dill ; extra == "extended"
Project-URL: Home, https://github.com/AlyceOsbourne/PythonicArchiveKit
Provides-Extra: all
Provides-Extra: encryption
Provides-Extra: extended
